CHANGELOG.txt
LICENSE.txt
MANIFEST.in
README.txt
setup.py
area_and_volume_calculator/__init__.py
area_and_volume_calculator.egg-info/PKG-INFO
area_and_volume_calculator.egg-info/SOURCES.txt
area_and_volume_calculator.egg-info/dependency_links.txt
area_and_volume_calculator.egg-info/top_level.txt