Metadata-Version: 2.1
Name: area-and-volume-calculator
Version: 0.0.1
Summary: Area and Volume Calculator
Home-page: UNKNOWN
Author: Murtaza Chulawala
Author-email: eklodokro@gmail.com
License: UNKNOWN
Platform: UNKNOWN
Classifier: Programming Language :: Python :: 3
Classifier: License :: OSI Approved :: MIT License
Classifier: Operating System :: OS Independent
License-File: LICENSE.txt
